sharemint/__init__.py
sharemint/ctx.py
sharemint/errors.py
sharemint/file.py
sharemint/folder.py
sharemint-0.0.3.dist-info/METADATA
sharemint-0.0.3.dist-info/WHEEL
sharemint-0.0.3.dist-info/top_level.txt
sharemint-0.0.3.dist-info/RECORD
