Metadata-Version: 2.1
Name: sharemint
Version: 0.0.3
Summary: SharePoint Interaction Tool - A package that allows users to interact with files & Folders in a SharePoint Website.
Author: Varun Mhatre
Keywords: python,sharepoint,download,upload,office365-sharepoint
Classifier: Development Status :: 1 - Planning
Classifier: Intended Audience :: Developers
Classifier: Programming Language :: Python :: 3
Classifier: Operating System :: Unix
Classifier: Operating System :: MacOS :: MacOS X
Classifier: Operating System :: Microsoft :: Windows
Requires-Dist: Office365-REST-Python-Client
Requires-Dist: python-dateutil
